pandafry/__init__.py
pandafry/pandafry.py
testingpackages/__init__.py
testingpackages/testingpackages.py
tests/__init__.py
tests/test_pandafry.py
tests/test_testingpackages.py
emfrytestingpackages-0.2.0.dist-info/LICENSE
emfrytestingpackages-0.2.0.dist-info/METADATA
emfrytestingpackages-0.2.0.dist-info/WHEEL
emfrytestingpackages-0.2.0.dist-info/top_level.txt
emfrytestingpackages-0.2.0.dist-info/RECORD
