Metadata-Version: 2.1
Name: emfrytestingpackages
Version: 0.2.0
Summary: A package that tests building packages
Home-page: https://github.com/yourusername/mypackage
Author: Emily Fry
Author-email: emfry1010@gmail.com
Classifier: Programming Language :: Python :: 3
Classifier: License :: OSI Approved :: MIT License
Classifier: Operating System :: OS Independent
Requires-Python: >=3.6
License-File: LICENSE
